sgraphic/__init__.py
sgraphic/animation.py
sgraphic/helpers.py
sgraphic/main.py
sgraphic/path.py
sgraphic/polygon.py
sgraphic-0.1.3.dist-info/LICENSE
sgraphic-0.1.3.dist-info/METADATA
sgraphic-0.1.3.dist-info/WHEEL
sgraphic-0.1.3.dist-info/top_level.txt
sgraphic-0.1.3.dist-info/RECORD
