Metadata-Version: 2.1
Name: sgraphic
Version: 0.1.3
Summary: Simple graphics. 
Home-page: https://github.com/ReneTC/Simple-graphics
Author: Rene Czepluch Thomsen
Author-email: sepluk1@gmail.com
License: BSD
Keywords: graphics package 2d
Platform: UNKNOWN
License-File: LICENSE
Requires-Dist: IPython
Requires-Dist: Pillow
Requires-Dist: easing-functions
Requires-Dist: numpy
Requires-Dist: skia-python
